headless_music/__init__.py
headless_music/config.py
headless_music/headless_music.py
headless_music/main.py
headless_music/player.py
headless_music/fetchers/__init__.py
headless_music/fetchers/spotify.py
headless_music/fetchers/youtube.py
headless_music/ui/__init__.py
headless_music/ui/art.py
headless_music/ui/layout.py
headless_music/ui/panels.py
headless_music/utils/__init__.py
headless_music/utils/cache.py
headless_music/utils/helpers.py
headless_music-1.1.0.dist-info/licenses/LICENSE
headless_music-1.1.0.dist-info/METADATA
headless_music-1.1.0.dist-info/WHEEL
headless_music-1.1.0.dist-info/entry_points.txt
headless_music-1.1.0.dist-info/top_level.txt
headless_music-1.1.0.dist-info/RECORD
