Metadata-Version: 2.4
Name: headless-music
Version: 1.1.0
Summary: headless music: for minimal cpu/gpu usage while listening to music
Author: Rishav Ganguly
License: MIT
Project-URL: Homepage, https://github.com/imnotgoingtohindiclass/headless_music
Requires-Python: >=3.8
License-File: LICENSE
Requires-Dist: yt-dlp
Requires-Dist: spotipy
Requires-Dist: python-mpv
Requires-Dist: rich
Dynamic: license-file
